demos/__init__.py
demos/test_batch.py
mbnpy/__init__.py
mbnpy/bnb_fns.py
mbnpy/branch.py
mbnpy/brc.py
mbnpy/config.py
mbnpy/cpm.py
mbnpy/inference.py
mbnpy/model.py
mbnpy/network.py
mbnpy/trans.py
mbnpy/utils.py
mbnpy/variable.py
mbnpy/extern/__init__.py
mbnpy/extern/dag.py
mbnpy/extern/pipeline.py
mbnpy/extern/tabulate.py
tests/__init__.py
tests/test_bnb.py
tests/test_bnb_fns.py
tests/test_branch.py
tests/test_brc.py
tests/test_cpm.py
tests/test_inference.py
tests/test_mcs_product.py
tests/test_model.py
tests/test_network.py
tests/test_trans.py
tests/test_variable.py
mbnpy-0.1.12.dist-info/METADATA
mbnpy-0.1.12.dist-info/WHEEL
mbnpy-0.1.12.dist-info/top_level.txt
mbnpy-0.1.12.dist-info/RECORD
