Metadata-Version: 2.4
Name: mbnpy
Version: 0.1.12
Summary: MBNpy is a Python package for Bayesian network applications for large-scale system events (i.e. high-dimensional data).
Home-page: https://github.com/jieunbyun/MBNpy
Author: The DUCO team
Author-email: ji-eun.byun@glasgow.ac.uk
Classifier: Programming Language :: Python :: 3
Classifier: Programming Language :: Python :: 3.8
Classifier: License :: OSI Approved :: MIT License
Classifier: Operating System :: OS Independent
Requires-Python: >=3.8
Requires-Dist: geopandas>=1.0
Requires-Dist: matplotlib>=3.10
Requires-Dist: networkx>=3.4
Requires-Dist: numpy>=2.2
Requires-Dist: pandas>=2.2
Requires-Dist: polyline>=2.0
Requires-Dist: pyarrow>=19.0
Requires-Dist: pytest>=8.3
Requires-Dist: scipy>=1.15
Requires-Dist: Shapely>=2.0
Requires-Dist: typer>=0.15
Requires-Dist: typing_extensions>=4.12
Requires-Dist: plotly>=6.2
Dynamic: author
Dynamic: author-email
Dynamic: classifier
Dynamic: description
Dynamic: description-content-type
Dynamic: home-page
Dynamic: requires-dist
Dynamic: requires-python
Dynamic: summary
